configurator/__init__.py
configurator/cli.py
configurator/constants.py
configurator/hosts/__init__.py
configurator/hosts/command.py
configurator/hosts/commands.py
configurator/hosts/host.py
configurator/tasks/__init__.py
configurator/tasks/commands.py
configurator/tasks/task.py
configurator/tasks/task_steps.py
atkinsonm_configurator-0.0.4.dist-info/METADATA
atkinsonm_configurator-0.0.4.dist-info/WHEEL
atkinsonm_configurator-0.0.4.dist-info/dependency_links.txt
atkinsonm_configurator-0.0.4.dist-info/entry_points.txt
atkinsonm_configurator-0.0.4.dist-info/top_level.txt
atkinsonm_configurator-0.0.4.dist-info/RECORD
