Metadata-Version: 2.1
Name: atkinsonm-configurator
Version: 0.0.4
Summary: A simple configuration management tool designed for performing administrative actions on Linux servers
Home-page: https://github.com/atkinsonm/slack-ops-challenge
Author: Mike Atkinson
Author-email: m.g.atkinson@outlook.com
License: UNKNOWN
Platform: UNKNOWN
Requires-Dist: click
Requires-Dist: dataclasses-json
Requires-Dist: paramiko
Requires-Dist: pkginfo
Requires-Dist: pyyaml
Requires-Dist: requests-toolbelt
Requires-Dist: twine
